{
  "all_item": [
    {
      "lang_setting": [
        "lang_app",
        "lang_app_ai_lover",
        "lang_web",
        "lang_bible",
        "lang_contact_store"
      ],
      "id_import": "lang"
    },
    {
      "js": "117.94",
      "icon_category": "2.60",
      "ebook": "3.40",
      "lang_web": "8.80",
      "app": "30.80",
      "background": "6.80",
      "user": "6.80",
      "icon": "11.81",
      "link_store": "11.85",
      "lang": "12.82",
      "song": "18.81",
      "audio": "1.20",
      "code": "19.82",
      "css": "5.80",
      "page": "15.83",
      "ebook_category": "4.50",
      "id_import": "version"
    }
  ],
  "collection": "setting_web"
}